{
  "row": {
    "spacing": {
      "spaceBetween": {
        "s": {
          "value": "{core.dimension.50}",
          "type": "spacing"
        },
        "none": {
          "value": "{core.dimension.0}",
          "type": "spacing"
        }
      },
      "spaceAround": {
        "s": {
          "value": "{core.dimension.75}, {core.dimension.50}",
          "type": "spacing"
        }
      }
    },
    "icon-size": {
      "s": {
        "value": "{semantic.size.icon.xs}",
        "type": "sizing"
      },
      "m": {
        "value": "{semantic.size.icon.l}",
        "type": "sizing"
      }
    },
    "icon-border-radius": {
      "pill": {
        "value": "{core.boder-radius.pill}",
        "type": "borderRadius"
      }
    },
    "border-color": {
      "top": {
        "value": {
          "color": "{semantic.color.action.cta.secondary.default.border-color}",
          "width": "1px",
          "style": "solid"
        },
        "type": "border"
      }
    },
    "cta": {
      "default": {
        "text-color": {
          "value": "{semantic.color.action.cta.secondary.default.text-color}",
          "type": "color"
        }
      },
      "hover": {
        "text-color": {
          "value": "{semantic.color.action.cta.secondary.hover.text-color}",
          "type": "color"
        }
      },
      "active": {
        "text-color": {
          "value": "{core.aquamarine.500}",
          "type": "color"
        }
      }
    }
  }
}